shroomdk/__init__.py
shroomdk/flipside.py
shroomdk/rpc.py
shroomdk/shroomdk.py
shroomdk/errors/__init__.py
shroomdk/errors/api_error.py
shroomdk/errors/base_error.py
shroomdk/errors/query_run_errors.py
shroomdk/errors/sdk_error.py
shroomdk/errors/server_error.py
shroomdk/integrations/__init__.py
shroomdk/integrations/query_integration/__init__.py
shroomdk/integrations/query_integration/compass_query_integration.py
shroomdk/integrations/query_integration/defaults.py
shroomdk/integrations/query_integration/query_result_set_builder.py
shroomdk/models/__init__.py
shroomdk/models/query.py
shroomdk/models/query_defaults.py
shroomdk/models/query_result_set.py
shroomdk/models/query_run_stats.py
shroomdk/models/query_status.py
shroomdk/models/sleep_config.py
shroomdk/models/compass/__init__.py
shroomdk/models/compass/cancel_query_run.py
shroomdk/models/compass/create_query_run.py
shroomdk/models/compass/get_query_run.py
shroomdk/models/compass/get_query_run_results.py
shroomdk/models/compass/get_sql_statement.py
shroomdk/models/compass/query_results.py
shroomdk/models/compass/core/__init__.py
shroomdk/models/compass/core/column_metadata.py
shroomdk/models/compass/core/page.py
shroomdk/models/compass/core/page_stats.py
shroomdk/models/compass/core/query_request.py
shroomdk/models/compass/core/query_run.py
shroomdk/models/compass/core/result_format.py
shroomdk/models/compass/core/rpc_error.py
shroomdk/models/compass/core/rpc_request.py
shroomdk/models/compass/core/rpc_response.py
shroomdk/models/compass/core/sql_statement.py
shroomdk/models/compass/core/tags.py
shroomdk/tests/__init__.py
shroomdk/tests/test_rpc.py
shroomdk/tests/integrations/__init__.py
shroomdk/tests/integrations/query_integration/__init__.py
shroomdk/tests/integrations/query_integration/test_query_compass_integration.py
shroomdk/tests/integrations/query_integration/test_query_result_set_builder.py
shroomdk/tests/models/__init__.py
shroomdk/tests/models/test_query_status.py
shroomdk/tests/utils/__init__.py
shroomdk-2.1.0.dist-info/LICENSE.txt
shroomdk-2.1.0.dist-info/METADATA
shroomdk-2.1.0.dist-info/WHEEL
shroomdk-2.1.0.dist-info/top_level.txt
shroomdk-2.1.0.dist-info/RECORD
